{
  "contentManagement": [
    {
    "title": "房屋管理",
    "icon": "icon-text",
   "href": "page/Owners/userOwner.html",
    "spread": false
    },{
      "title": "车位管理",
      "icon": "icon-text",
      "href": "page/news/newsList.html",
      "spread": false,
      "children": [
        {"title": "车位信息",
          "icon": "&#xe61c;",
          "href": "page/parking/parkingOwner.html",
          "spread": false
       }
                   ]
     },{
      "title": "信息管理",
      "icon": "icon-text",
      "href": "page/news/newsList.html",
      "spread": false,
      "children": [
        {
          "title": "申请消息",
          "icon": "&#xe61c;",
          "href": "page/message/message.html",
          "spread": false
        }
      ]
    },{
      "title": "查看公告",
      "icon": "&#xe62a;",
      "href": "page/announcement/announcementOwner.html",
      "spread": false
    },{
      "title": "缴费 ",
      "icon": "icon-text",
      "href": "page/payment/paymentDeatilInfoOwner.html",
      "spread": false
    }
  ]

}


